Workbook

Sheet README
A1: Kaveri Retail Ltd - three-statement model
A3: How to read this workbook
A4: Blue text = a hardcoded input. Every assumption in the model is blue, and blue is the only
A5: font colour you should ever type over.
A6: Black text = a formula. If you type over black text you have broken the model.
A7: Green text = a link to another sheet in this workbook.
A8: Yellow fill = the checks block. It must read zero.
A10: What this is
A11: A complete, balancing three-statement forecast model. Use it as the target to compare your
A12: own build against - not as something to copy. Build yours first, then open this one.
A14: Sheets
A15: Assumptions every forecast driver, with the FY26 actual beside it for comparison
... A36: working capital, and it is the single most common thing juniors get wrong.

Sheet Assumptions
A1: Kaveri Retail Ltd (KVRA) - forecast assumptions
A2: Fiscal year ends 31 March. All amounts in Rs millions unless stated.
A4: Every forecast driver is anchored to what the business actually did in FY26.
A5: If you change an assumption, say why in the note column.
A7: Driver | B7: FY26A | C7: FY27E | D7: FY28E | E7: FY29E | F7: FY30E | G7: FY31E
A8: Revenue growth (%) | B8: =Model!D7 -> 9207 | C8: 0.06 | D8: 0.055 | E8: 0.05 | F8: 0.045 | G8: 0.04
A9: Gross margin (%) | B9: =Model!D11 -> 0.42000652 | C9: 0.42 | D9: 0.42 | E9: 0.421 | F9: 0.421 | G9: 0.422
A10: Operating expenses (% of revenue) | B10: =Model!D14 -> 0.13500597 | C10: 0.285 | D10: 0.285 | E10: 0.284 | F10: 0.284 | G10: 0.283
A11: Depreciation (% of opening net PPE) | B11: =Model!D46 -> 0.08124667 | C11: 0.08 | D11: 0.08 | E11: 0.08 | F11: 0.08 | G11: 0.08
A12: Amortisation (% of opening intangibles) | B12: =Model!D53 -> 0.058823529 | C12: 0.06 | D12: 0.06 | E12: 0.06 | F12: 0.06 | G12: 0.06
A13: Capex (% of revenue) | B13: =Model!D47 -> 3909 | C13: 0.05 | D13: 0.05 | E13: 0.049 | F13: 0.049 | G13: 0.048
A14: Days sales outstanding (DSO) | B14: =Model!D28 -> 30.644618 | C14: 30.6 | D14: 30.6 | E14: 30 | F14: 30 | G14: 30
A15: Days inventory outstanding (DIO) | B15: =Model!D30 -> 76.622659 | C15: 76.6 | D15: 76 | E15: 75 | F15: 75 | G15: 75
A16: Days payable outstanding (DPO) | B16: =Model!D33 -> 51.058989 | C16: 51.1 | D16: 51 | E16: 51 | F16: 51 | G16: 51
A17: Other current assets (% of revenue) | B17: =Model!D35 -> 0.012816335 | C17: 0.0128 | D17: 0.0128 | E17: 0.0128 | F17: 0.0128 | G17: 0.0128
A18: Accrued liabilities (% of revenue) | B18: =Model!D36 -> 0.010209623 | C18: 0.0102 | D18: 0.0102 | E18: 0.0102 | F18: 0.0102 | G18: 0.0102
A19: Deferred revenue (% of revenue) | B19: =Model!D37 -> 0.012816335 | C19: 0.0128 | D19: 0.0128 | E19: 0.0128 | F19: 0.0128 | G19: 0.0128
A20: Interest rate on opening total debt (%) | B20: =Model!D60 -> 0.10056926 | C20: 0.1 | D20: 0.1 | E20: 0.1 | F20: 0.1 | G20: 0.1
A21: Interest earned on opening cash (%) | B21: =Model!D61 -> 2120 | C21: 0.024 | D21: 0.024 | E21: 0.024 | F21: 0.024 | G21: 0.024
A22: Effective tax rate (%) | B22: =Model!D62 -> 0.25 | C22: 0.25 | D22: 0.25 | E22: 0.25 | F22: 0.25 | G22: 0.25
A23: Scheduled debt repayment (Rs m) | B23: 223 | C23: 223 | D23: 223 | E23: 223 | F23: 223 | G23: 223
A24: Dividend payout (% of net income) | B24: 0 | C24: 0 | D24: 0 | E24: 0 | F24: 0 | G24: 0
A26: Blue = you may change it. Green = pulled from the Model sheet's actuals.
A27: Note: interest is charged on OPENING debt, not average debt. That removes the
A28: circular reference entirely, at the cost of a little precision. See Module 14.

Sheet Model
A1: Kaveri Retail Ltd (KVRA) - three-statement model
A2: Rs millions, fiscal years ending 31 March
A3: FY24-FY26 are actuals (blue). FY27-FY31 are formulas, identical across every forecast column.
A5: Fiscal year | B5: FY24A | C5: FY25A | D5: FY26A | E5: FY27E | F5: FY28E | G5: FY29E | H5: FY30E | I5: FY31E
A6: INCOME STATEMENT
A7: Revenue | B7: 8249 | C7: 8671 | D7: 9207 | E7: =D7*(1+Assumptions!C8) -> 9759.42 | F7: =E7*(1+Assumptions!D8) -> 10296.188 | G7: =F7*(1+Assumptions!E8) -> 10810.998 | H7: =G7*(1+Assumptions!F8) -> 11297.492 | I7: =H7*(1+Assumptions!G8) -> 11749.392
A8: Revenue growth (%) | C8: =C7/B7-1 -> 0.051157716 | D8: =D7/C7-1 -> 0.061815246 | E8: =E7/D7-1 -> 0.06 | F8: =F7/E7-1 -> 0.055 | G8: =G7/F7-1 -> 0.05 | H8: =H7/G7-1 -> 0.045 | I8: =I7/H7-1 -> 0.04
A9: Cost of goods sold | B9: 4784 | C9: 5029 | D9: 5340 | E9: =E7*(1-Assumptions!C9) -> 5660.4636 | F9: =F7*(1-Assumptions!D9) -> 5971.7891 | G9: =G7*(1-Assumptions!E9) -> 6259.5676 | H9: =H7*(1-Assumptions!F9) -> 6541.2481 | I9: =I7*(1-Assumptions!G9) -> 6791.1486
A10: Gross profit | B10: =B7-B9 -> 3465 | C10: =C7-C9 -> 3642 | D10: =D7-D9 -> 3867 | E10: =E7-E9 -> 4098.9564 | F10: =F7-F9 -> 4324.399 | G10: =G7-G9 -> 4551.4299 | H10: =H7-H9 -> 4756.2443 | I10: =I7-I9 -> 4958.2435
A11: Gross margin (%) | B11: =B10/B7 -> 0.42005092 | C11: =C10/C7 -> 0.42002076 | D11: =D10/D7 -> 0.42000652 | E11: =E10/E7 -> 0.42 | F11: =F10/F7 -> 0.42 | G11: =G10/G7 -> 0.421 | H11: =H10/H7 -> 0.421 | I11: =I10/I7 -> 0.422
A12: Operating expenses | B12: 2351 | C12: 2471 | D12: 2624 | E12: =E7*Assumptions!C10 -> 2781.4347 | F12: =F7*Assumptions!D10 -> 2934.4136 | G12: =G7*Assumptions!E10 -> 3070.3233 | H12: =H7*Assumptions!F10 -> 3208.4878 | I12: =I7*Assumptions!G10 -> 3325.078
A13: EBITDA | B13: =B10-B12 -> 1114 | C13: =C10-C12 -> 1171 | D13: =D10-D12 -> 1243 | E13: =E10-E12 -> 1317.5217 | F13: =F10-F12 -> 1389.9854 | G13: =G10-G12 -> 1481.1067 | H13: =H10-H12 -> 1547.7565 | I13: =I10-I12 -> 1633.1655
A14: EBITDA margin (%) | B14: =B13/B7 -> 0.13504667 | C14: =C13/C7 -> 0.13504786 | D14: =D13/D7 -> 0.13500597 | E14: =E13/E7 -> 0.135 | F14: =F13/F7 -> 0.135 | G14: =G13/G7 -> 0.137 | H14: =H13/H7 -> 0.137 | I14: =I13/I7 -> 0.139
A15: Depreciation | B15: 284 | C15: 293 | D15: 305 | E15: =E48 -> 312.72 | F15: =F48 -> 326.74008 | G15: =G48 -> 341.78563 | H15: =H48 -> 356.82189 | I15: =I48 -> 372.56231
A16: Amortisation | B16: 8 | C16: 7 | D16: 7 | E16: =E54 -> 6.72 | F16: =F54 -> 6.3168 | G16: =G54 -> 5.937792 | H16: =H54 -> 5.5815245 | I16: =I54 -> 5.246633
A17: EBIT | B17: =B13-B15-B16 -> 822 | C17: =C13-C15-C16 -> 871 | D17: =D13-D15-D16 -> 931 | E17: =E13-E15-E16 -> 998.0817 | F17: =F13-F15-F16 -> 1056.9285 | G17: =G13-G15-G16 -> 1133.3832 | H17: =H13-H15-H16 -> 1185.353 | I17: =I13-I15-I16 -> 1255.3566
A18: Interest expense | B18: 312 | C18: 288 | D18: 265 | E18: =D64*Assumptions!C20 -> 241.2 | F18: =E64*Assumptions!D20 -> 218.9 | G18: =F64*Assumptions!E20 -> 196.6 | H18: =G64*Assumptions!F20 -> 174.3 | I18: =H64*Assumptions!G20 -> 152
A19: Interest income | B19: 82 | C19: 83 | D19: 86 | E19: =D82*Assumptions!C21 -> 87.864 | F19: =E82*Assumptions!D21 -> 92.206328 | G19: =F82*Assumptions!E21 -> 97.962218 | H19: =G82*Assumptions!F21 -> 106.32251 | I19: =H82*Assumptions!G21 -> 115.21002
A20: Profit before tax | B20: =B17-B18+B19 -> 592 | C20: =C17-C18+C19 -> 666 | D20: =D17-D18+D19 -> 752 | E20: =E17-E18+E19 -> 844.7457 | F20: =F17-F18+F19 -> 930.23484 | G20: =G17-G18+G19 -> 1034.7455 | H20: =H17-H18+H19 -> 1117.3756 | I20: =I17-I18+I19 -> 1218.5666
A21: Tax | B21: 148 | C21: 166 | D21: 188 | E21: =MAX(E20,0)*Assumptions!C22 -> 211.18643 | F21: =MAX(F20,0)*Assumptions!D22 -> 232.55871 | G21: =MAX(G20,0)*Assumptions!E22 -> 258.68636 | H21: =MAX(H20,0)*Assumptions!F22 -> 279.34389 | I21: =MAX(I20,0)*Assumptions!G22 -> 304.64164
A22: Net income | B22: =B20-B21 -> 444 | C22: =C20-C21 -> 500 | D22: =D20-D21 -> 564 | E22: =E20-E21 -> 633.55927 | F22: =F20-F21 -> 697.67613 | G22: =G20-G21 -> 776.05909 | H22: =H20-H21 -> 838.03167 | I22: =I20-I21 -> 913.92493
A23: Net margin (%) | B23: =B22/B7 -> 0.053824706 | C23: =C22/C7 -> 0.057663476 | D23: =D22/D7 -> 0.061257739 | E23: =E22/E7 -> 0.064917718 | F23: =F22/F7 -> 0.067760624 | G23: =G22/G7 -> 0.071784226 | H23: =H22/H7 -> 0.074178556 | I23: =I22/I7 -> 0.07778487
A24: Dividends paid | B24: 0 | C24: 0 | D24: 0 | E24: =MAX(E22,0)*Assumptions!C24 -> 0 | F24: =MAX(F22,0)*Assumptions!D24 -> 0 | G24: =MAX(G22,0)*Assumptions!E24 -> 0 | H24: =MAX(H22,0)*Assumptions!F24 -> 0 | I24: =MAX(I22,0)*Assumptions!G24 -> 0
A26: WORKING CAPITAL SCHEDULE
A27: Accounts receivable | B27: 730 | C27: 726 | D27: 773 | E27: =Assumptions!C14/365*E7 -> 818.18699 | F27: =Assumptions!D14/365*F7 -> 863.18728 | G27: =Assumptions!E14/365*G7 -> 888.57514 | H27: =Assumptions!F14/365*H7 -> 928.56102 | I27: =Assumptions!G14/365*I7 -> 965.70346
A28: DSO (days) | B28: =B27/B7*365 -> 32.300885 | C28: =C27/C7*365 -> 30.560489 | D28: =D27/D7*365 -> 30.644618 | E28: =E27/E7*365 -> 30.6 | F28: =F27/F7*365 -> 30.6 | G28: =G27/G7*365 -> 30 | H28: =H27/H7*365 -> 30 | I28: =I27/I7*365 -> 30
A29: Inventory | B29: 1058 | C29: 1053 | D29: 1121 | E29: =Assumptions!C15/365*E9 -> 1187.922 | F29: =Assumptions!D15/365*F9 -> 1243.441 | G29: =Assumptions!E15/365*G9 -> 1286.2125 | H29: =Assumptions!F15/365*H9 -> 1344.0921 | I29: =Assumptions!G15/365*I9 -> 1395.4415
A30: DIO (days) | B30: =B29/B9*365 -> 80.721154 | C30: =C29/C9*365 -> 76.425731 | D30: =D29/D9*365 -> 76.622659 | E30: =E29/E9*365 -> 76.6 | F30: =F29/F9*365 -> 76 | G30: =G29/G9*365 -> 75 | H30: =H29/H9*365 -> 75 | I30: =I29/I9*365 -> 75
A31: Other current assets | B31: 111 | C31: 110 | D31: 118 | E31: =E7*Assumptions!C17 -> 124.92058 | F31: =F7*Assumptions!D17 -> 131.79121 | G31: =G7*Assumptions!E17 -> 138.38077 | H31: =H7*Assumptions!F17 -> 144.6079 | I31: =I7*Assumptions!G17 -> 150.39222
A32: Accounts payable | B32: 705 | C32: 702 | D32: 747 | E32: =Assumptions!C16/365*E9 -> 792.4649 | F32: =Assumptions!D16/365*F9 -> 834.41437 | G32: =Assumptions!E16/365*G9 -> 874.62451 | H32: =Assumptions!F16/365*H9 -> 913.98261 | I32: =Assumptions!G16/365*I9 -> 948.90022
A33: DPO (days) | B33: =B32/B9*365 -> 53.788671 | C33: =C32/C9*365 -> 50.950487 | D33: =D32/D9*365 -> 51.058989 | E33: =E32/E9*365 -> 51.1 | F33: =F32/F9*365 -> 51 | G33: =G32/G9*365 -> 51 | H33: =H32/H9*365 -> 51 | I33: =I32/I9*365 -> 51
A34: Accrued liabilities | B34: 89 | C34: 88 | D34: 94 | E34: =E7*Assumptions!C18 -> 99.546084 | F34: =F7*Assumptions!D18 -> 105.02112 | G34: =G7*Assumptions!E18 -> 110.27217 | H34: =H7*Assumptions!F18 -> 115.23442 | I34: =I7*Assumptions!G18 -> 119.8438
A35: Other current assets (% of revenue) | B35: =B31/B7 -> 0.013456177 | C35: =C31/C7 -> 0.012685965 | D35: =D31/D7 -> 0.012816335 | E35: =E31/E7 -> 0.0128 | F35: =F31/F7 -> 0.0128 | G35: =G31/G7 -> 0.0128 | H35: =H31/H7 -> 0.0128 | I35: =I31/I7 -> 0.0128
A36: Accrued liabilities (% of revenue) | B36: =B34/B7 -> 0.010789187 | C36: =C34/C7 -> 0.010148772 | D36: =D34/D7 -> 0.010209623 | E36: =E34/E7 -> 0.0102 | F36: =F34/F7 -> 0.0102 | G36: =G34/G7 -> 0.0102 | H36: =H34/H7 -> 0.0102 | I36: =I34/I7 -> 0.0102
A37: Deferred revenue (% of revenue) | B37: =B38/B7 -> 0.013456177 | C37: =C38/C7 -> 0.012685965 | D37: =D38/D7 -> 0.012816335 | E37: =E38/E7 -> 0.0128 | F37: =F38/F7 -> 0.0128 | G37: =G38/G7 -> 0.0128 | H37: =H38/H7 -> 0.0128 | I37: =I38/I7 -> 0.0128
A38: Deferred revenue | B38: 111 | C38: 110 | D38: 118 | E38: =E7*Assumptions!C19 -> 124.92058 | F38: =F7*Assumptions!D19 -> 131.79121 | G38: =G7*Assumptions!E19 -> 138.38077 | H38: =H7*Assumptions!F19 -> 144.6079 | I38: =I7*Assumptions!G19 -> 150.39222
A39: Net working capital | B39: =B27+B29+B31-B32-B34-B38 -> 994 | C39: =C27+C29+C31-C32-C34-C38 -> 989 | D39: =D27+D29+D31-D32-D34-D38 -> 1053 | E39: =E27+E29+E31-E32-E34-E38 -> 1114.098 | F39: =F27+F29+F31-F32-F34-F38 -> 1167.1928 | G39: =G27+G29+G31-G32-G34-G38 -> 1189.891 | H39: =H27+H29+H31-H32-H34-H38 -> 1243.4361 | I39: =I27+I29+I31-I32-I34-I38 -> 1292.4009
A40: Change in net working capital | C40: =C39-B39 -> -5 | D40: =D39-C39 -> 64 | E40: =E39-D39 -> 61.097954 | F40: =F39-E39 -> 53.094854 | G40: =G39-F39 -> 22.698158 | H40: =H39-G39 -> 53.545093 | I40: =I39-H39 -> 48.96488
A41: Cash impact of working capital | C41: =-C40 -> 5 | D41: =-D40 -> -64 | E41: =-E40 -> -61.097954 | F41: =-F40 -> -53.094854 | G41: =-G40 -> -22.698158 | H41: =-H40 -> -53.545093 | I41: =-I40 -> -48.96488
A43: FIXED ASSET AND INTANGIBLE SCHEDULES
A44: Opening net PPE | C44: =B47 -> 3619 | D44: =C47 -> 3754 | E44: =D47 -> 3909 | F44: =E47 -> 4084.251 | G44: =F47 -> 4272.3203 | H44: =G47 -> 4460.2736 | I44: =H47 -> 4657.0288
A45: Capex | B45: 400 | C45: 429 | D45: 460 | E45: =E7*Assumptions!C13 -> 487.971 | F45: =F7*Assumptions!D13 -> 514.8094 | G45: =G7*Assumptions!E13 -> 529.73888 | H45: =H7*Assumptions!F13 -> 553.57713 | I45: =I7*Assumptions!G13 -> 563.97082
A46: Depreciation (% of opening PPE) | C46: =C48/C44 -> 0.080961592 | D46: =D48/D44 -> 0.08124667 | E46: =E48/E44 -> 0.08 | F46: =F48/F44 -> 0.08 | G46: =G48/G44 -> 0.08 | H46: =H48/H44 -> 0.08 | I46: =I48/I44 -> 0.08
A47: Closing net PPE | B47: 3619 | C47: 3754 | D47: 3909 | E47: =E44+E45-E48 -> 4084.251 | F47: =F44+F45-F48 -> 4272.3203 | G47: =G44+G45-G48 -> 4460.2736 | H47: =H44+H45-H48 -> 4657.0288 | I47: =I44+I45-I48 -> 4848.4373
A48: Depreciation | B48: 284 | C48: 293 | D48: 305 | E48: =E44*Assumptions!C11 -> 312.72 | F48: =F44*Assumptions!D11 -> 326.74008 | G48: =G44*Assumptions!E11 -> 341.78563 | H48: =H44*Assumptions!F11 -> 356.82189 | I48: =I44*Assumptions!G11 -> 372.56231
A49: Capex (% of revenue) [historical check] | B49: =B45/B7 -> 0.048490726 | C49: =C45/C7 -> 0.049475262 | D49: =D45/D7 -> 0.049961985 | E49: =E45/E7 -> 0.05 | F49: =F45/F7 -> 0.05 | G49: =G45/G7 -> 0.049 | H49: =H45/H7 -> 0.049 | I49: =I45/I7 -> 0.048
A51: Opening intangibles | C51: =B55 -> 126 | D51: =C55 -> 119 | E51: =D55 -> 112 | F51: =E55 -> 105.28 | G51: =F55 -> 98.9632 | H51: =G55 -> 93.025408 | I51: =H55 -> 87.443884
A52: Amortisation | B52: 8 | C52: 7 | D52: 7 | E52: =E54 -> 6.72 | F52: =F54 -> 6.3168 | G52: =G54 -> 5.937792 | H52: =H54 -> 5.5815245 | I52: =I54 -> 5.246633
A53: Amortisation (% of opening intangibles) | C53: =C52/C51 -> 0.055555556 | D53: =D52/D51 -> 0.058823529 | E53: =E52/E51 -> 0.06 | F53: =F52/F51 -> 0.06 | G53: =G52/G51 -> 0.06 | H53: =H52/H51 -> 0.06 | I53: =I52/I51 -> 0.06
A54: Amortisation charge | B54: 8 | C54: 7 | D54: 7 | E54: =E51*Assumptions!C12 -> 6.72 | F54: =F51*Assumptions!D12 -> 6.3168 | G54: =G51*Assumptions!E12 -> 5.937792 | H54: =H51*Assumptions!F12 -> 5.5815245 | I54: =I51*Assumptions!G12 -> 5.246633
A55: Closing intangibles | B55: 126 | C55: 119 | D55: 112 | E55: =E51-E54 -> 105.28 | F55: =F51-F54 -> 98.9632 | G55: =G51-G54 -> 93.025408 | H55: =H51-H54 -> 87.443884 | I55: =I51-I54 -> 82.197251
A57: DEBT SCHEDULE
A58: Opening long-term debt | C58: =B61 -> 2566 | D58: =C61 -> 2343 | E58: =D61 -> 2120 | F58: =E61 -> 1897 | G58: =F61 -> 1674 | H58: =G61 -> 1451 | I58: =H61 -> 1228
A59: Scheduled repayment | B59: 223 | C59: 223 | D59: 223 | E59: =MIN(Assumptions!C23,E58) -> 223 | F59: =MIN(Assumptions!D23,F58) -> 223 | G59: =MIN(Assumptions!E23,G58) -> 223 | H59: =MIN(Assumptions!F23,H58) -> 223 | I59: =MIN(Assumptions!G23,I58) -> 223
A60: Interest rate on opening total debt (%) | C60: =C18/B64 -> 0.10076977 | D60: =D18/C64 -> 0.10056926 | E60: =E18/D64 -> 0.1 | F60: =F18/E64 -> 0.1 | G60: =G18/F64 -> 0.1 | H60: =H18/G64 -> 0.1 | I60: =I18/H64 -> 0.1
A61: Closing long-term debt | B61: 2566 | C61: 2343 | D61: 2120 | E61: =E58-E59 -> 1897 | F61: =F58-F59 -> 1674 | G61: =G58-G59 -> 1451 | H61: =H58-H59 -> 1228 | I61: =I58-I59 -> 1005
A62: Effective tax rate (%) | B62: =B21/B20 -> 0.25 | C62: =C21/C20 -> 0.24924925 | D62: =D21/D20 -> 0.25 | E62: =E21/E20 -> 0.25 | F62: =F21/F20 -> 0.25 | G62: =G21/G20 -> 0.25 | H62: =H21/H20 -> 0.25 | I62: =I21/I20 -> 0.25
A63: Short-term debt | B63: 292 | C63: 292 | D63: 292 | E63: =D63 -> 292 | F63: =E63 -> 292 | G63: =F63 -> 292 | H63: =G63 -> 292 | I63: =H63 -> 292
A64: Total debt | B64: =B61+B63 -> 2858 | C64: =C61+C63 -> 2635 | D64: =D61+D63 -> 2412 | E64: =E61+E63 -> 2189 | F64: =F61+F63 -> 1966 | G64: =G61+G63 -> 1743 | H64: =H61+H63 -> 1520 | I64: =I61+I63 -> 1297
A66: CASH FLOW STATEMENT
A67: Net income | C67: =C22 -> 500 | D67: =D22 -> 564 | E67: =E22 -> 633.55927 | F67: =F22 -> 697.67613 | G67: =G22 -> 776.05909 | H67: =H22 -> 838.03167 | I67: =I22 -> 913.92493
A68: Add back: depreciation and amortisation | C68: =C15+C16 -> 300 | D68: =D15+D16 -> 312 | E68: =E15+E16 -> 319.44 | F68: =F15+F16 -> 333.05688 | G68: =G15+G16 -> 347.72342 | H68: =H15+H16 -> 362.40341 | I68: =I15+I16 -> 377.80894
A69: Change in working capital | C69: =C41 -> 5 | D69: =D41 -> -64 | E69: =E41 -> -61.097954 | F69: =F41 -> -53.094854 | G69: =G41 -> -22.698158 | H69: =H41 -> -53.545093 | I69: =I41 -> -48.96488
A70: Cash from operations | C70: =SUM(C67:C69) -> 805 | D70: =SUM(D67:D69) -> 812 | E70: =SUM(E67:E69) -> 891.90132 | F70: =SUM(F67:F69) -> 977.63816 | G70: =SUM(G67:G69) -> 1101.0844 | H70: =SUM(H67:H69) -> 1146.89 | I70: =SUM(I67:I69) -> 1242.769
A71: Capital expenditure | C71: =-C45 -> -429 | D71: =-D45 -> -460 | E71: =-E45 -> -487.971 | F71: =-F45 -> -514.8094 | G71: =-G45 -> -529.73888 | H71: =-H45 -> -553.57713 | I71: =-I45 -> -563.97082
A72: Cash from investing | C72: =C71 -> -429 | D72: =D71 -> -460 | E72: =E71 -> -487.971 | F72: =F71 -> -514.8094 | G72: =G71 -> -529.73888 | H72: =H71 -> -553.57713 | I72: =I71 -> -563.97082
A73: Debt repayment | C73: =-C59 -> -223 | D73: =-D59 -> -223 | E73: =-E59 -> -223 | F73: =-F59 -> -223 | G73: =-G59 -> -223 | H73: =-H59 -> -223 | I73: =-I59 -> -223
A74: Dividends paid | C74: =-C24 -> 0 | D74: =-D24 -> 0 | E74: =-E24 -> 0 | F74: =-F24 -> 0 | G74: =-G24 -> 0 | H74: =-H24 -> 0 | I74: =-I24 -> 0
A75: Cash from financing | C75: =SUM(C73:C74) -> -223 | D75: =SUM(D73:D74) -> -223 | E75: =SUM(E73:E74) -> -223 | F75: =SUM(F73:F74) -> -223 | G75: =SUM(G73:G74) -> -223 | H75: =SUM(H73:H74) -> -223 | I75: =SUM(I73:I74) -> -223
A76: Other, including rounding | C76: =C82-(B82+C70+C72+C75) -> -1 | D76: =D82-(C82+D70+D72+D75) -> 0 | E76: 0 | F76: 0 | G76: 0 | H76: 0 | I76: 0
A77: Net change in cash | C77: =C70+C72+C75+C76 -> 152 | D77: =D70+D72+D75+D76 -> 129 | E77: =E70+E72+E75+E76 -> 180.93032 | F77: =F70+F72+F75+F76 -> 239.82875 | G77: =G70+G72+G75+G76 -> 348.34548 | H77: =H70+H72+H75+H76 -> 370.31286 | I77: =I70+I72+I75+I76 -> 455.79817
A78: Opening cash | C78: =B82 -> 3380 | D78: =C82 -> 3532 | E78: =D82 -> 3661 | F78: =E82 -> 3841.9303 | G78: =F82 -> 4081.7591 | H78: =G82 -> 4430.1045 | I78: =H82 -> 4800.4174
A79: Closing cash | C79: =C78+C77 -> 3532 | D79: =D78+D77 -> 3661 | E79: =E78+E77 -> 3841.9303 | F79: =F78+F77 -> 4081.7591 | G79: =G78+G77 -> 4430.1045 | H79: =H78+H77 -> 4800.4174 | I79: =I78+I77 -> 5256.2156
A80: (memo) unlevered free cash flow | C80: =C17*(1-C62)+C15+C16-C45+C41 -> 529.9039 | D80: =D17*(1-D62)+D15+D16-D45+D41 -> 486.25 | E80: =E17*(1-E62)+E15+E16-E45+E41 -> 518.93232 | F80: =F17*(1-F62)+F15+F16-F45+F41 -> 557.84901 | G80: =G17*(1-G62)+G15+G16-G45+G41 -> 645.32381 | H80: =H17*(1-H62)+H15+H16-H45+H41 -> 644.29598 | I80: =I17*(1-I62)+I15+I16-I45+I41 -> 706.39066
A81: BALANCE SHEET
A82: Cash | B82: 3380 | C82: 3532 | D82: 3661 | E82: =E79 -> 3841.9303 | F82: =F79 -> 4081.7591 | G82: =G79 -> 4430.1045 | H82: =H79 -> 4800.4174 | I82: =I79 -> 5256.2156
A83: Accounts receivable | B83: 730 | C83: 726 | D83: 773 | E83: =E27 -> 818.18699 | F83: =F27 -> 863.18728 | G83: =G27 -> 888.57514 | H83: =H27 -> 928.56102 | I83: =I27 -> 965.70346
A84: Inventory | B84: 1058 | C84: 1053 | D84: 1121 | E84: =E29 -> 1187.922 | F84: =F29 -> 1243.441 | G84: =G29 -> 1286.2125 | H84: =H29 -> 1344.0921 | I84: =I29 -> 1395.4415
A85: Other current assets | B85: 111 | C85: 110 | D85: 118 | E85: =E31 -> 124.92058 | F85: =F31 -> 131.79121 | G85: =G31 -> 138.38077 | H85: =H31 -> 144.6079 | I85: =I31 -> 150.39222
A86: Net property, plant and equipment | B86: 3619 | C86: 3754 | D86: 3909 | E86: =E47 -> 4084.251 | F86: =F47 -> 4272.3203 | G86: =G47 -> 4460.2736 | H86: =H47 -> 4657.0288 | I86: =I47 -> 4848.4373
A87: Goodwill and intangibles | B87: 126 | C87: 119 | D87: 112 | E87: =E55 -> 105.28 | F87: =F55 -> 98.9632 | G87: =G55 -> 93.025408 | H87: =H55 -> 87.443884 | I87: =I55 -> 82.197251
A88: Other assets | B88: 195 | C88: 195 | D88: 195 | E88: =D88 -> 195 | F88: =E88 -> 195 | G88: =F88 -> 195 | H88: =G88 -> 195 | I88: =H88 -> 195
A89: Total assets | B89: =SUM(B82:B88) -> 9219 | C89: =SUM(C82:C88) -> 9489 | D89: =SUM(D82:D88) -> 9889 | E89: =SUM(E82:E88) -> 10357.491 | F89: =SUM(F82:F88) -> 10886.462 | G89: =SUM(G82:G88) -> 11491.572 | H89: =SUM(H82:H88) -> 12157.151 | I89: =SUM(I82:I88) -> 12893.387
A90: Accounts payable | B90: 705 | C90: 702 | D90: 747 | E90: =E32 -> 792.4649 | F90: =F32 -> 834.41437 | G90: =G32 -> 874.62451 | H90: =H32 -> 913.98261 | I90: =I32 -> 948.90022
A91: Accrued liabilities | B91: 89 | C91: 88 | D91: 94 | E91: =E34 -> 99.546084 | F91: =F34 -> 105.02112 | G91: =G34 -> 110.27217 | H91: =H34 -> 115.23442 | I91: =I34 -> 119.8438
A92: Deferred revenue | B92: 111 | C92: 110 | D92: 118 | E92: =E38 -> 124.92058 | F92: =F38 -> 131.79121 | G92: =G38 -> 138.38077 | H92: =H38 -> 144.6079 | I92: =I38 -> 150.39222
A93: Short-term debt | B93: 292 | C93: 292 | D93: 292 | E93: =E63 -> 292 | F93: =F63 -> 292 | G93: =G63 -> 292 | H93: =H63 -> 292 | I93: =I63 -> 292
A94: Long-term debt | B94: 2566 | C94: 2343 | D94: 2120 | E94: =E61 -> 1897 | F94: =F61 -> 1674 | G94: =G61 -> 1451 | H94: =H61 -> 1228 | I94: =I61 -> 1005
A95: Other liabilities | B95: 117 | C95: 117 | D95: 117 | E95: =D95 -> 117 | F95: =E95 -> 117 | G95: =F95 -> 117 | H95: =G95 -> 117 | I95: =H95 -> 117
A96: Total liabilities | B96: =SUM(B90:B95) -> 3880 | C96: =SUM(C90:C95) -> 3652 | D96: =SUM(D90:D95) -> 3488 | E96: =SUM(E90:E95) -> 3322.9316 | F96: =SUM(F90:F95) -> 3154.2267 | G96: =SUM(G90:G95) -> 2983.2775 | H96: =SUM(H90:H95) -> 2810.8249 | I96: =SUM(I90:I95) -> 2633.1362
A97: Share capital | B97: 973 | C97: 973 | D97: 973 | E97: =D97 -> 973 | F97: =E97 -> 973 | G97: =F97 -> 973 | H97: =G97 -> 973 | I97: =H97 -> 973
A98: Retained earnings | B98: 4366 | C98: 4864 | D98: 5428 | E98: =D98+E22-E24 -> 6061.5593 | F98: =E98+F22-F24 -> 6759.2354 | G98: =F98+G22-G24 -> 7535.2945 | H98: =G98+H22-H24 -> 8373.3262 | I98: =H98+I22-I24 -> 9287.2511
A99: Total equity | B99: =B97+B98 -> 5339 | C99: =C97+C98 -> 5837 | D99: =D97+D98 -> 6401 | E99: =E97+E98 -> 7034.5593 | F99: =F97+F98 -> 7732.2354 | G99: =G97+G98 -> 8508.2945 | H99: =H97+H98 -> 9346.3262 | I99: =I97+I98 -> 10260.251
A100: Total liabilities and equity | B100: =B96+B99 -> 9219 | C100: =C96+C99 -> 9489 | D100: =D96+D99 -> 9889 | E100: =E96+E99 -> 10357.491 | F100: =F96+F99 -> 10886.462 | G100: =G96+G99 -> 11491.572 | H100: =H96+H99 -> 12157.151 | I100: =I96+I99 -> 12893.387
A102: CHECKS (every cell must read zero)
A103: 1. Balance sheet: total assets less total liabilities and equity | B103: =B89-B100 -> 0 | C103: =C89-C100 -> 0 | D103: =D89-D100 -> 0 | E103: =E89-E100 -> 0 | F103: =F89-F100 -> 0 | G103: =G89-G100 -> 0 | H103: =H89-H100 -> 0 | I103: =I89-I100 -> 0
A104: 2. Cash link: balance sheet cash less cash flow closing cash (FY25 onwards) | C104: =C82-C79 -> 0 | D104: =D82-D79 -> 0 | E104: =E82-E79 -> 0 | F104: =F82-F79 -> 0 | G104: =G82-G79 -> 0 | H104: =H82-H79 -> 0 | I104: =I82-I79 -> 0
A105: 3. Debt link: balance sheet debt less debt schedule total debt | B105: =B93+B94-B64 -> 0 | C105: =C93+C94-C64 -> 0 | D105: =D93+D94-D64 -> 0 | E105: =E93+E94-E64 -> 0 | F105: =F93+F94-F64 -> 0 | G105: =G93+G94-G64 -> 0 | H105: =H93+H94-H64 -> 0 | I105: =I93+I94-I64 -> 0
A107: MODEL OK? | B107: =IF(SUMPRODUCT(ABS(B103:I105))<0.5,"OK","ERROR - see checks above") -> OK
A109: Why check 1 can be trusted: cash is NOT plugged in this model. It is built up from the cash flow
...
