Workbook

Sheet README
A1: Kaveri Retail Ltd - leveraged buyout model
A3: How to read this workbook
A4: Blue text = a hardcoded input. Every assumption in the model is blue, and blue is the only
A5: font colour you should ever type over.
A6: Black text = a formula. If you type over black text you have broken the model.
A7: Green text = a link to another sheet in this workbook.
A8: Yellow fill = the checks block. It must read zero.
A10: What this is
A11: A five-year LBO: sources and uses, an operating and debt model with a cash sweep, sponsor
A12: returns with attribution, a paper-LBO drill, and IRR sensitivity.
A14: Sheets
A15: Assumptions what you pay, how much you borrow, what you sell for
... A48: and you should say so out loud rather than burying it in a cell.

Sheet Assumptions
A1: Kaveri Retail Ltd (KVRA) - LBO assumptions
A2: Rs millions. Assumed close 31-Mar-2026, five-year hold to 31-Mar-2031.
A4: Input | B4: Value | C4: Note
A5: LTM EBITDA at entry | B5: 1243 | C5: FY26 actual
A6: Entry EV / EBITDA multiple | B6: 11 | C6: What you are willing to pay. The premium falls out of this.
A7: Entry leverage (x EBITDA) | B7: 4 | C7: How much debt the lenders will provide
A8: Transaction fees (% of EV) | B8: 0.02 | C8: Advisory, financing and legal
A9: Interest rate on term loan | B9: 0.11 | C9: Floating rate plus margin
A10: Mandatory amortisation (% of original) | B10: 0.01 | C10: Contractual repayment each year
A11: Cash sweep (% of surplus) | B11: 1 | C11: Share of free cash flow that must repay debt
A12: Tax rate | B12: 0.25 | C12: Effective rate
A13: Exit EV / EBITDA multiple | B13: 11 | C13: Assume you sell at what you paid. Anything better is luck.
A14: Hold period (years) | B14: 5
A15: Existing debt refinanced | B15: 2412 | C15: Balance sheet at 31-Mar-2026
A16: Cash on the balance sheet | B16: 3661 | C16: Balance sheet at 31-Mar-2026, used to fund the deal
A17: Shares outstanding (m) | B17: 87.17 | C17: dim_company.shares_out_m
A18: Share price before the deal (Rs) | B18: 149.6865 | C18: Close on 31-Mar-2026
A20: DERIVED FROM THE ABOVE
A21: Entry enterprise value | B21: =B5*B6 -> 13673
A22: New term loan | B22: =B5*B7 -> 4972
A23: Transaction fees | B23: =B21*B8 -> 273.46
A24: Equity purchase price | B24: =B21+B16-B15 -> 14922 | C24: enterprise value plus cash acquired less debt assumed
A25: Implied offer per share (Rs) | B25: =B24/B17 -> 171.18275
A26: Implied premium to the undisturbed price | B26: =B25/B18-1 -> 0.14360845
A27: The premium is an OUTPUT, not an input. Raise the entry multiple and you can
A28: offer more; the returns then have to survive it. That trade-off is the whole job.

Sheet Sources and Uses
A1: Sources and uses of funds
A3: USES | B3: Rs m | C3: % of total
A4: Purchase of equity | B4: =Assumptions!B24 -> 14922 | C4: =B4/$B$7 -> 0.84748169
A5: Refinance existing debt | B5: =Assumptions!B15 -> 2412 | C5: =B5/$B$7 -> 0.13698739
A6: Transaction fees | B6: =Assumptions!B23 -> 273.46 | C6: =B6/$B$7 -> 0.015530917
A7: Total uses | B7: =SUM(B4:B6) -> 17607.46 | C7: =B7/$B$7 -> 1
A9: SOURCES | B9: Rs m | C9: % of total | D9: x EBITDA
A10: New term loan B | B10: =Assumptions!B22 -> 4972 | C10: =B10/$B$13 -> 0.28238031 | D10: =B10/Assumptions!B5 -> 4
A11: Cash on the balance sheet | B11: =Assumptions!B16 -> 3661 | C11: =B11/$B$13 -> 0.20792323
A12: Sponsor equity | B12: =B7-B10-B11 -> 8974.46 | C12: =B12/$B$13 -> 0.50969646
A13: Total sources | B13: =SUM(B10:B12) -> 17607.46 | C13: =B13/$B$13 -> 1
A15: CHECK: sources less uses | B15: =B13-B7 -> 0 | D15: must be zero, always, before anything else is believed
A17: Equity as % of total capitalisation | B17: =B12/(B10+B12) -> 0.64349376
A18: Opening net debt / EBITDA | B18: =B10/Assumptions!B5 -> 4

Sheet Model
A1: Kaveri Retail Ltd - LBO operating and debt model
A2: Rs millions. Operating forecast carried over from the three-statement model.
A4: Fiscal year | B4: FY27E | C4: FY28E | D4: FY29E | E4: FY30E | F4: FY31E
A5: OPERATING FORECAST
A6: EBITDA | B6: 1317.5 | C6: 1390 | D6: 1481.1 | E6: 1547.8 | F6: 1633.2 | G6: from workbook 01, Model!E13:I13
A7: Depreciation and amortisation | B7: 319.4 | C7: 333 | D7: 347.7 | E7: 362.4 | F7: 377.8
A8: Capital expenditure | B8: 488 | C8: 514.8 | D8: 529.7 | E8: 553.6 | F8: 564
A9: Change in working capital (cash impact) | B9: -61.1 | C9: -53.1 | D9: -22.7 | E9: -53.5 | F9: -49
A10: EBIT | B10: =B6-B7 -> 998.1 | C10: =C6-C7 -> 1057 | D10: =D6-D7 -> 1133.4 | E10: =E6-E7 -> 1185.4 | F10: =F6-F7 -> 1255.4
A12: DEBT SCHEDULE AND CASH SWEEP
A13: Opening term loan | B13: ='Sources and Uses'!B10 -> 4972 | C13: =B21 -> 4863.315 | D13: =C21 -> 4706.6885 | E13: =D21 -> 4449.6403 | F13: =E21 -> 4172.3856
A14: Interest expense | B14: =B13*Assumptions!$B$9 -> 546.92 | C14: =C13*Assumptions!$B$9 -> 534.96465 | D14: =D13*Assumptions!$B$9 -> 517.73573 | E14: =E13*Assumptions!$B$9 -> 489.46043 | F14: =F13*Assumptions!$B$9 -> 458.96242
A15: Profit before tax | B15: =B10-B14 -> 451.18 | C15: =C10-C14 -> 522.03535 | D15: =D10-D14 -> 615.66427 | E15: =E10-E14 -> 695.93957 | F15: =F10-F14 -> 796.43758
A16: Tax | B16: =MAX(B15,0)*Assumptions!$B$12 -> 112.795 | C16: =MAX(C15,0)*Assumptions!$B$12 -> 130.50884 | D16: =MAX(D15,0)*Assumptions!$B$12 -> 153.91607 | E16: =MAX(E15,0)*Assumptions!$B$12 -> 173.98489 | F16: =MAX(F15,0)*Assumptions!$B$12 -> 199.1094
A17: Net income | B17: =B15-B16 -> 338.385 | C17: =C15-C16 -> 391.52651 | D17: =D15-D16 -> 461.7482 | E17: =E15-E16 -> 521.95468 | F17: =F15-F16 -> 597.32819
A18: Free cash flow before debt service | B18: =B17+B7-B8+B9 -> 108.685 | C18: =C17+C7-C8+C9 -> 156.62651 | D18: =D17+D7-D8+D9 -> 257.0482 | E18: =E17+E7-E8+E9 -> 277.25468 | F18: =F17+F7-F8+F9 -> 362.12819
A19: Mandatory amortisation | B19: =-MIN(Assumptions!$B$10*'Sources and Uses'!$B$10,B13) -> -49.72 | C19: =-MIN(Assumptions!$B$10*'Sources and Uses'!$B$10,C13) -> -49.72 | D19: =-MIN(Assumptions!$B$10*'Sources and Uses'!$B$10,D13) -> -49.72 | E19: =-MIN(Assumptions!$B$10*'Sources and Uses'!$B$10,E13) -> -49.72 | F19: =-MIN(Assumptions!$B$10*'Sources and Uses'!$B$10,F13) -> -49.72
A20: Cash sweep | B20: =-MIN(MAX(B18+B19,0)*Assumptions!$B$11,B13+B19) -> -58.965 | C20: =-MIN(MAX(C18+C19,0)*Assumptions!$B$11,C13+C19) -> -106.90651 | D20: =-MIN(MAX(D18+D19,0)*Assumptions!$B$11,D13+D19) -> -207.3282 | E20: =-MIN(MAX(E18+E19,0)*Assumptions!$B$11,E13+E19) -> -227.53468 | F20: =-MIN(MAX(F18+F19,0)*Assumptions!$B$11,F13+F19) -> -312.40819
A21: Closing term loan | B21: =B13+B19+B20 -> 4863.315 | C21: =C13+C19+C20 -> 4706.6885 | D21: =D13+D19+D20 -> 4449.6403 | E21: =E13+E19+E20 -> 4172.3856 | F21: =F13+F19+F20 -> 3810.2574
A22: Cash retained in the business | B22: =MAX(B18+B19+B20,0) -> 0 | C22: =B22+MAX(C18+C19+C20,0) -> 0 | D22: =C22+MAX(D18+D19+D20,0) -> 0 | E22: =D22+MAX(E18+E19+E20,0) -> 0 | F22: =E22+MAX(F18+F19+F20,0) -> 0
A23: Net debt | B23: =B21-B22 -> 4863.315 | C23: =C21-C22 -> 4706.6885 | D23: =D21-D22 -> 4449.6403 | E23: =E21-E22 -> 4172.3856 | F23: =F21-F22 -> 3810.2574
A24: Net debt / EBITDA | B24: =B23/B6 -> 3.6913207 | C24: =C23/C6 -> 3.3861068 | D24: =D23/D6 -> 3.0042808 | E24: =E23/E6 -> 2.6956878 | F24: =F23/F6 -> 2.3330011
A25: EBITDA / interest (interest cover) | B25: =B6/B14 -> 2.4089446 | C25: =C6/C14 -> 2.5983025 | D25: =D6/D14 -> 2.8607259 | E25: =E6/E14 -> 3.1622577 | F25: =F6/F14 -> 3.5584613
A26: Covenant: net debt / EBITDA must stay below | B26: 5.5 | C26: 5.5 | D26: 5.5 | E26: 5.5 | F26: 5.5
A27: Covenant test | B27: =IF(B24<B26,"PASS","BREACH") -> PASS | C27: =IF(C24<C26,"PASS","BREACH") -> PASS | D27: =IF(D24<D26,"PASS","BREACH") -> PASS | E27: =IF(E24<E26,"PASS","BREACH") -> PASS | F27: =IF(F24<F26,"PASS","BREACH") -> PASS

Sheet Returns
A1: Sponsor returns
A3: EXIT
A4: Exit year EBITDA | B4: =Model!F6 -> 1633.2
A5: Exit multiple | B5: =Assumptions!B13 -> 11
A6: Exit enterprise value | B6: =B4*B5 -> 17965.2
A7: Less: net debt at exit | B7: =-Model!F23 -> -3810.2574
A8: Equity value at exit | B8: =B6+B7 -> 14154.943
A10: CASH FLOWS TO THE SPONSOR | B10: Close | C10: FY27 | D10: FY28 | E10: FY29 | F10: FY30 | G10: FY31
A11: Equity in / (out) | B11: =-'Sources and Uses'!B12 -> -8974.46 | C11: 0 | D11: 0 | E11: 0 | F11: 0 | G11: =B8 -> 14154.943
A13: Money multiple (MoM) | B13: =B8/'Sources and Uses'!B12 -> 1.5772473
A14: Internal rate of return (IRR) | B14: =IRR(B11:G11) -> 0.095418212
A15: IRR cross-check from the multiple | B15: =B13^(1/Assumptions!B14)-1 -> 0.095418212 | C15: should equal the IRR above when there are no interim cash flows
A17: WHERE THE MONEY CAME FROM
A18: Value created for the sponsor | B18: =B8-'Sources and Uses'!B12 -> 5180.4826
A19: EBITDA growth, held at the entry multiple | B19: =(B4-Assumptions!B5)*Assumptions!B6 -> 4292.2 | C19: =B19/$B$18 -> 0.82853285 | D19: this is operational work - it is the part you control
A20: Multiple expansion, on exit EBITDA | B20: =(B5-Assumptions!B6)*B4 -> 0 | C20: =B20/$B$18 -> 0 | D20: this is the market being kind to you - it is luck
A21: Debt paydown and cash build | B21: =Assumptions!B22-Model!F23 -> 1161.7426 | C21: =B21/$B$18 -> 0.22425374 | D21: the company's own cash flow repaying the borrowing
A22: Fees and other | B22: =B18-B19-B20-B21 -> -273.46 | C22: =B22/$B$18 -> -0.052786588
A23: Total | B23: =SUM(B19:B22) -> 5180.4826 | C23: =SUM(C19:C22) -> 1
A24: CHECK: total less value created | B24: =B23-B18 -> 0
A27: THE PAPER LBO - practise this until you can do it out loud in five minutes
A28: Entry EBITDA | B28: 100
A29: Entry multiple | B29: 10
A30: Entry enterprise value | B30: =B28*B29 -> 1000
A31: Debt (x EBITDA) | B31: 6
A32: Debt raised | B32: =B28*B31 -> 600
A33: Sponsor equity | B33: =B30-B32 -> 400
A34: EBITDA in year 5 | B34: 150
A35: Debt repaid over the hold | B35: 300
A36: Debt at exit | B36: =B32-B35 -> 300
A37: Exit multiple | B37: 10
A38: Exit enterprise value | B38: =B34*B37 -> 1500
A39: Equity at exit | B39: =B38-B36 -> 1200
A40: Money multiple | B40: =B39/B33 -> 3
A41: IRR (5 years) | B41: =B40^(1/5)-1 -> 0.24573094
A42: Memorise the mapping: over five years 2.0x is about 15% IRR, 2.5x about 20%,
A43: 3.0x about 25%, 4.0x about 32%. Interviewers expect it instantly.

Sheet Sensitivity
A1: Sensitivity - sponsor IRR
A2: Entry multiple down the side, exit multiple across the top.
A3: Debt raised is a multiple of EBITDA, so it does not move with the entry multiple -
A4: only the size of the equity cheque does. That is why this grid is exact and not an
A5: approximation.
A7: Entry \ Exit | B7: 9 | C7: 10 | D7: 11 | E7: 12 | F7: 13
A8: 9 | B8: =((B$7*Model!$F$6-Model!$F$23)/($A8*Assumptions!$B$5*(1+Assumptions!$B$8)-Assumptions!$B$22))^(1/Assumptions!$B$14)-1 -> 0.11079463 | C8: =((C$7*Model!$F$6-Model!$F$23)/($A8*Assumptions!$B$5*(1+Assumptions!$B$8)-Assumptions!$B$22))^(1/Assumptions!$B$14)-1 -> 0.14228054 | D8: =((D$7*Model!$F$6-Model!$F$23)/($A8*Assumptions!$B$5*(1+Assumptions!$B$8)-Assumptions!$B$22))^(1/Assumptions!$B$14)-1 -> 0.17063484 | E8: =((E$7*Model!$F$6-Model!$F$23)/($A8*Assumptions!$B$5*(1+Assumptions!$B$8)-Assumptions!$B$22))^(1/Assumptions!$B$14)-1 -> 0.19648162 | F8: =((F$7*Model!$F$6-Model!$F$23)/($A8*Assumptions!$B$5*(1+Assumptions!$B$8)-Assumptions!$B$22))^(1/Assumptions!$B$14)-1 -> 0.2202706
A9: 10 | B9: =((B$7*Model!$F$6-Model!$F$23)/($A9*Assumptions!$B$5*(1+Assumptions!$B$8)-Assumptions!$B$22))^(1/Assumptions!$B$14)-1 -> 0.071572074 | C9: =((C$7*Model!$F$6-Model!$F$23)/($A9*Assumptions!$B$5*(1+Assumptions!$B$8)-Assumptions!$B$22))^(1/Assumptions!$B$14)-1 -> 0.1019462 | D9: =((D$7*Model!$F$6-Model!$F$23)/($A9*Assumptions!$B$5*(1+Assumptions!$B$8)-Assumptions!$B$22))^(1/Assumptions!$B$14)-1 -> 0.1292993 | E9: =((E$7*Model!$F$6-Model!$F$23)/($A9*Assumptions!$B$5*(1+Assumptions!$B$8)-Assumptions!$B$22))^(1/Assumptions!$B$14)-1 -> 0.15423342 | F9: =((F$7*Model!$F$6-Model!$F$23)/($A9*Assumptions!$B$5*(1+Assumptions!$B$8)-Assumptions!$B$22))^(1/Assumptions!$B$14)-1 -> 0.1771824
A10: 11 | B10: =((B$7*Model!$F$6-Model!$F$23)/($A10*Assumptions!$B$5*(1+Assumptions!$B$8)-Assumptions!$B$22))^(1/Assumptions!$B$14)-1 -> 0.039422911 | C10: =((C$7*Model!$F$6-Model!$F$23)/($A10*Assumptions!$B$5*(1+Assumptions!$B$8)-Assumptions!$B$22))^(1/Assumptions!$B$14)-1 -> 0.068885754 | D10: =((D$7*Model!$F$6-Model!$F$23)/($A10*Assumptions!$B$5*(1+Assumptions!$B$8)-Assumptions!$B$22))^(1/Assumptions!$B$14)-1 -> 0.095418212 | E10: =((E$7*Model!$F$6-Model!$F$23)/($A10*Assumptions!$B$5*(1+Assumptions!$B$8)-Assumptions!$B$22))^(1/Assumptions!$B$14)-1 -> 0.11960426 | F10: =((F$7*Model!$F$6-Model!$F$23)/($A10*Assumptions!$B$5*(1+Assumptions!$B$8)-Assumptions!$B$22))^(1/Assumptions!$B$14)-1 -> 0.14186473
A11: 12 | B11: =((B$7*Model!$F$6-Model!$F$23)/($A11*Assumptions!$B$5*(1+Assumptions!$B$8)-Assumptions!$B$22))^(1/Assumptions!$B$14)-1 -> 0.012311761 | C11: =((C$7*Model!$F$6-Model!$F$23)/($A11*Assumptions!$B$5*(1+Assumptions!$B$8)-Assumptions!$B$22))^(1/Assumptions!$B$14)-1 -> 0.041006128 | D11: =((D$7*Model!$F$6-Model!$F$23)/($A11*Assumptions!$B$5*(1+Assumptions!$B$8)-Assumptions!$B$22))^(1/Assumptions!$B$14)-1 -> 0.066846543 | E11: =((E$7*Model!$F$6-Model!$F$23)/($A11*Assumptions!$B$5*(1+Assumptions!$B$8)-Assumptions!$B$22))^(1/Assumptions!$B$14)-1 -> 0.09040175 | F11: =((F$7*Model!$F$6-Model!$F$23)/($A11*Assumptions!$B$5*(1+Assumptions!$B$8)-Assumptions!$B$22))^(1/Assumptions!$B$14)-1 -> 0.1120816
A12: 13 | B12: =((B$7*Model!$F$6-Model!$F$23)/($A12*Assumptions!$B$5*(1+Assumptions!$B$8)-Assumptions!$B$22))^(1/Assumptions!$B$14)-1 -> -0.011042729 | C12: =((C$7*Model!$F$6-Model!$F$23)/($A12*Assumptions!$B$5*(1+Assumptions!$B$8)-Assumptions!$B$22))^(1/Assumptions!$B$14)-1 -> 0.016989646 | D12: =((D$7*Model!$F$6-Model!$F$23)/($A12*Assumptions!$B$5*(1+Assumptions!$B$8)-Assumptions!$B$22))^(1/Assumptions!$B$14)-1 -> 0.04223391 | E12: =((E$7*Model!$F$6-Model!$F$23)/($A12*Assumptions!$B$5*(1+Assumptions!$B$8)-Assumptions!$B$22))^(1/Assumptions!$B$14)-1 -> 0.065245688 | F12: =((F$7*Model!$F$6-Model!$F$23)/($A12*Assumptions!$B$5*(1+Assumptions!$B$8)-Assumptions!$B$22))^(1/Assumptions!$B$14)-1 -> 0.086425376
A15: Money multiple
A16: Entry \ Exit | B16: 9 | C16: 10 | D16: 11 | E16: 12 | F16: 13
A17: 9 | B17: =(B$16*Model!$F$6-Model!$F$23)/($A17*Assumptions!$B$5*(1+Assumptions!$B$8)-Assumptions!$B$22) -> 1.6910983 | C17: =(C$16*Model!$F$6-Model!$F$23)/($A17*Assumptions!$B$5*(1+Assumptions!$B$8)-Assumptions!$B$22) -> 1.9447505 | D17: =(D$16*Model!$F$6-Model!$F$23)/($A17*Assumptions!$B$5*(1+Assumptions!$B$8)-Assumptions!$B$22) -> 2.1984026 | E17: =(E$16*Model!$F$6-Model!$F$23)/($A17*Assumptions!$B$5*(1+Assumptions!$B$8)-Assumptions!$B$22) -> 2.4520547 | F17: =(F$16*Model!$F$6-Model!$F$23)/($A17*Assumptions!$B$5*(1+Assumptions!$B$8)-Assumptions!$B$22) -> 2.7057068
A18: 10 | B18: =(B$16*Model!$F$6-Model!$F$23)/($A18*Assumptions!$B$5*(1+Assumptions!$B$8)-Assumptions!$B$22) -> 1.4128854 | C18: =(C$16*Model!$F$6-Model!$F$23)/($A18*Assumptions!$B$5*(1+Assumptions!$B$8)-Assumptions!$B$22) -> 1.6248076 | D18: =(D$16*Model!$F$6-Model!$F$23)/($A18*Assumptions!$B$5*(1+Assumptions!$B$8)-Assumptions!$B$22) -> 1.8367299 | E18: =(E$16*Model!$F$6-Model!$F$23)/($A18*Assumptions!$B$5*(1+Assumptions!$B$8)-Assumptions!$B$22) -> 2.0486521 | F18: =(F$16*Model!$F$6-Model!$F$23)/($A18*Assumptions!$B$5*(1+Assumptions!$B$8)-Assumptions!$B$22) -> 2.2605744
A19: 11 | B19: =(B$16*Model!$F$6-Model!$F$23)/($A19*Assumptions!$B$5*(1+Assumptions!$B$8)-Assumptions!$B$22) -> 1.2132811 | C19: =(C$16*Model!$F$6-Model!$F$23)/($A19*Assumptions!$B$5*(1+Assumptions!$B$8)-Assumptions!$B$22) -> 1.3952642 | D19: =(D$16*Model!$F$6-Model!$F$23)/($A19*Assumptions!$B$5*(1+Assumptions!$B$8)-Assumptions!$B$22) -> 1.5772473 | E19: =(E$16*Model!$F$6-Model!$F$23)/($A19*Assumptions!$B$5*(1+Assumptions!$B$8)-Assumptions!$B$22) -> 1.7592304 | F19: =(F$16*Model!$F$6-Model!$F$23)/($A19*Assumptions!$B$5*(1+Assumptions!$B$8)-Assumptions!$B$22) -> 1.9412135
A20: 12 | B20: =(B$16*Model!$F$6-Model!$F$23)/($A20*Assumptions!$B$5*(1+Assumptions!$B$8)-Assumptions!$B$22) -> 1.0630934 | C20: =(C$16*Model!$F$6-Model!$F$23)/($A20*Assumptions!$B$5*(1+Assumptions!$B$8)-Assumptions!$B$22) -> 1.2225494 | D20: =(D$16*Model!$F$6-Model!$F$23)/($A20*Assumptions!$B$5*(1+Assumptions!$B$8)-Assumptions!$B$22) -> 1.3820055 | E20: =(E$16*Model!$F$6-Model!$F$23)/($A20*Assumptions!$B$5*(1+Assumptions!$B$8)-Assumptions!$B$22) -> 1.5414616 | F20: =(F$16*Model!$F$6-Model!$F$23)/($A20*Assumptions!$B$5*(1+Assumptions!$B$8)-Assumptions!$B$22) -> 1.7009176
A21: 13 | B21: =(B$16*Model!$F$6-Model!$F$23)/($A21*Assumptions!$B$5*(1+Assumptions!$B$8)-Assumptions!$B$22) -> 0.94599238 | C21: =(C$16*Model!$F$6-Model!$F$23)/($A21*Assumptions!$B$5*(1+Assumptions!$B$8)-Assumptions!$B$22) -> 1.0878842 | D21: =(D$16*Model!$F$6-Model!$F$23)/($A21*Assumptions!$B$5*(1+Assumptions!$B$8)-Assumptions!$B$22) -> 1.229776 | E21: =(E$16*Model!$F$6-Model!$F$23)/($A21*Assumptions!$B$5*(1+Assumptions!$B$8)-Assumptions!$B$22) -> 1.3716677 | F21: =(F$16*Model!$F$6-Model!$F$23)/($A21*Assumptions!$B$5*(1+Assumptions!$B$8)-Assumptions!$B$22) -> 1.5135595
